QtLogger/__init__.py
QtLogger/__main__.py
QtLogger/base.py
QtLogger/exceptions.py
QtLogger/warnings.py
QtLogger-1.0.3.dist-info/METADATA
QtLogger-1.0.3.dist-info/WHEEL
QtLogger-1.0.3.dist-info/top_level.txt
QtLogger-1.0.3.dist-info/RECORD
