Metadata-Version: 2.1
Name: QtLogger
Version: 1.0.3
Summary: A simple logger for PyQt6 that also has a nice UI
Home-page: https://github.com/Advik-B/PyQt-Logger
Author: Advik
Author-email: <advik.b@gmail.com>
Keywords: Logger,Qt,PyQt,Qt6,PyQt6,QtLogger
Classifier: Intended Audience :: Developers
Classifier: Programming Language :: Python :: 3
Classifier: License :: OSI Approved :: MIT License
Classifier: Operating System :: OS Independent
Requires-Dist: PyQt6
